Metadata-Version: 2.1
Name: nepali-transliteration
Version: 0.5
Summary: Convert roman English to Nepali text
Home-page: https://github.com/santoshdahal2016/nepali-transliteration
Author: Santosh Dahal
Author-email: dahalsantosh2018@gmail.com
License: UNKNOWN
Platform: UNKNOWN
Classifier: Programming Language :: Python :: 3
Classifier: License :: OSI Approved :: MIT License
Classifier: Operating System :: OS Independent
